aily/__init__.py
aily/innerapi/__init__.py
aily/innerapi/app.py
aily/innerapi/llm.py
aily/innerapi/message.py
aily/message/__init__.py
aily/message/button.py
aily/message/chart.py
aily/message/field.py
aily/message/record.py
aily/message/table.py
aily/message/utils.py
aily/openapi/__init__.py
aily/openapi/assistant/__init__.py
aily/openapi/assistant/beta.py
aily/openapi/assistant/errors.py
aily/openapi/assistant/langchain_llm.py
aily/openapi/data.py
aily/openapi/feishu/__init__.py
aily/openapi/feishu/card_message.py
aily/openapi/meta.py
aily/util/__init__.py
aily/util/channel_context.py
aily/util/sidebar.py
aily_sdk-0.30.0.dist-info/LICENSE
aily_sdk-0.30.0.dist-info/METADATA
aily_sdk-0.30.0.dist-info/WHEEL
aily_sdk-0.30.0.dist-info/RECORD
