Metadata-Version: 2.1
Name: aily-sdk
Version: 0.30.0
Summary: 
Author: lijiuyang.5137
Author-email: lijiuyang.5137@bytedance.com
Requires-Python: >=3.8.1,<4.0.0
Classifier: Programming Language :: Python :: 3
Classifier: Programming Language :: Python :: 3.9
Classifier: Programming Language :: Python :: 3.10
Classifier: Programming Language :: Python :: 3.11
Requires-Dist: langchain (>=0.1.16,<0.2.0)
Requires-Dist: loguru (>=0.7.2,<0.8.0)
Requires-Dist: requests (>=2.31.0,<3.0.0)
